ACM-traingui/__main__.py
ACM-traingui/labeling_gui.py
ACM-traingui/labeling_gui_cfg.py
ACMtraingui/__main__.py
ACMtraingui/config.py
ACMtraingui/labeling_gui.py
ACMtraingui/labeling_gui_cfg.py
bbo_acm_traingui-0.11.7.dist-info/LICENSE
bbo_acm_traingui-0.11.7.dist-info/METADATA
bbo_acm_traingui-0.11.7.dist-info/WHEEL
bbo_acm_traingui-0.11.7.dist-info/top_level.txt
bbo_acm_traingui-0.11.7.dist-info/RECORD
