Metadata-Version: 2.1
Name: bbo-acm-traingui
Version: 0.11.7
Summary: GUI to label frames for training of ACM-dlcdetect
Home-page: https://github.com/bbo-lab/acm-traingui
Author: BBO-lab @ caesar
Author-email: kay-michael.voit@caesar.de
License: BSD
Platform: UNKNOWN
Classifier: License :: OSI Approved :: BSD License
Classifier: Programming Language :: Python :: 3
Classifier: Programming Language :: Python :: 3.6
Classifier: Programming Language :: Python :: 3.7
Classifier: Programming Language :: Python :: 3.8
Classifier: Programming Language :: Python :: 3.9
License-File: LICENSE
Requires-Dist: numpy
